bilibili_dl/__init__.py
bilibili_dl/cli.py
bilibili_dl/main.py
bilibili_dl/version.py
bilibili_dl/src/Video.py
bilibili_dl/src/__init__.py
bilibili_dl/src/constants.py
bilibili_dl/src/downloader.py
bilibili_dl/src/utils.py
bilibili_dl-3.2.1.dist-info/LICENSE
bilibili_dl-3.2.1.dist-info/METADATA
bilibili_dl-3.2.1.dist-info/WHEEL
bilibili_dl-3.2.1.dist-info/entry_points.txt
bilibili_dl-3.2.1.dist-info/top_level.txt
bilibili_dl-3.2.1.dist-info/RECORD
