Metadata-Version: 2.1
Name: bilibili-dl
Version: 3.2.1
Summary: Bilibili-dl 是一个下载B站音视频的工具（目前视频下载最高只支持720P）
Home-page: https://github.com/Youguang-Zhou/bilibili-dl
License-File: LICENSE
Requires-Dist: tqdm
Requires-Dist: requests
Requires-Dist: progressbar
